richtemplates/__init__.py
richtemplates/altair_theme.py
richtemplates/data.py
richtemplates/plotly_theme.py
richtemplates/tutorial.py
richtemplates-0.0.1.dist-info/METADATA
richtemplates-0.0.1.dist-info/WHEEL
richtemplates-0.0.1.dist-info/top_level.txt
richtemplates-0.0.1.dist-info/RECORD
